babel/__init__.py
babel/ont.py
scripts/__init__.py
scripts/benchmark_ont.py
scripts/benchmark_ont_clips.py
syntreenet/__init__.py
syntreenet/core.py
syntreenet/factset.py
syntreenet/logging.py
syntreenet/ruleset.py
syntreenet/util.py
syntreenet/babel/__init__.py
syntreenet/babel/ont.py
syntreenet/scripts/__init__.py
syntreenet/scripts/benchmark_ont.py
syntreenet/scripts/benchmark_ont_clips.py
syntreenet-0.1.0a11.dist-info/LICENSE.txt
syntreenet-0.1.0a11.dist-info/METADATA
syntreenet-0.1.0a11.dist-info/WHEEL
syntreenet-0.1.0a11.dist-info/top_level.txt
syntreenet-0.1.0a11.dist-info/RECORD
