Metadata-Version: 2.1
Name: syntreenet
Version: 0.1.0a11
Summary: A library to develop scalable production rule systems
Home-page: http://www.syntree.net/
Author: Enrique Pérez Arnaud
Author-email: enrique@cazalla.net
License: GPLv3
Platform: UNKNOWN
Classifier: Programming Language :: Python :: 3
Classifier: License :: OSI Approved :: GNU General Public License v3 (GPLv3)
Classifier: Operating System :: OS Independent
